Metadata-Version: 2.1
Name: pickshot
Version: 0.1.0
Home-page: https://github.com/jkubis96/PickShot/tree/main
Author: Jakub Kubis - JBS
Author-email: Your Name <you@example.com>
License: GPL-3
Keywords: CNN,ML,QC,Flow cytometry,images,drop,microscopy
Classifier: Development Status :: 3 - Alpha
Classifier: Programming Language :: Python :: 3
Classifier: Operating System :: MacOS :: MacOS X
Classifier: Operating System :: Microsoft :: Windows
Classifier: Operating System :: POSIX :: Linux
Requires-Python: >=3.12,<3.13
License-File: LICENSE
